hippo_plot/__init__.py
hippo_plot/cli.py
hippo_plot/draw.py
hippo_plot/io.py
hippo_plot/prep.py
hippo_plot-0.0.7.dist-info/METADATA
hippo_plot-0.0.7.dist-info/WHEEL
hippo_plot-0.0.7.dist-info/entry_points.txt
hippo_plot-0.0.7.dist-info/RECORD
